[
  {
    "id": "annonce-devfest-2016",
    "title": "Le DevFest Toulouse 2016 est annoncé",
    "posted": "2016-06-20",
    "primaryColor": "#607D8B",
    "secondaryColor": "#607D8B",
    "image": "/images/posts/announce.jpg",
    "brief": "C'est désormais officiel, le DevFest Toulouse est lancé!"
  },
  {
    "id": "call-for-speakers",
    "title": "Appel à Orateurs",
    "posted": "2016-06-21",
    "primaryColor": "#673AB7",
    "secondaryColor": "#673AB7",
    "image": "/images/posts/speakers.jpg",
    "brief": "Le CFP est ouvert, venez soumettre vos sujets."
  },
  {
    "id": "que-faire-a-toulouse",
    "title": "Que faire à Toulouse ?",
    "posted": "2016-08-21",
    "primaryColor": "#0097a7",
    "secondaryColor": "#b2ebf2",
    "image": "/images/posts/capitole.jpg",
    "brief": "Si vous voulez des idées de sorties pendant que vous êtes par chez nous."
  },
  {
    "id": "ouverture-billeterie-annonce-premiers-speakers",
    "title": "Ouverture de la billeterie",
    "posted": "2016-09-01",
    "primaryColor": "#0097a7",
    "secondaryColor": "#b2ebf2",
    "image": "/images/posts/billetterie.jpg",
    "brief": "On en profite pour vous annoncer les premiers speakers."
  },
  {
    "id": "fermeture-cfp",
    "title": "Le CFP est fermé",
    "posted": "2016-09-29",
    "primaryColor": "#673AB7",
    "secondaryColor": "#673AB7",
    "image": "/images/posts/cloture_cfp.jpg",
    "brief": "Pour vous faire patienter avant le programme final."
  },
  {
    "id": "annonce-programme",
    "title": "Annonce des speakers et du programme.",
    "posted": "2016-09-30",
    "primaryColor": "#673AB7",
    "secondaryColor": "#673AB7",
    "image": "/images/posts/speakers.jpg",
    "brief": "Enfin, voici la liste des speakers et des talks sélectionnés"
  }
]
